shenafield/__init__.py
shenafield/cli.py
shenafield/shenafield.py
shenafield-0.1.4.dist-info/LICENSE
shenafield-0.1.4.dist-info/METADATA
shenafield-0.1.4.dist-info/WHEEL
shenafield-0.1.4.dist-info/entry_points.txt
shenafield-0.1.4.dist-info/RECORD
