Metadata-Version: 2.1
Name: shenafield
Version: 0.1.4
Summary: A library that replicates how shenafield talks
Home-page: https://github.com/shenafield/shenafield-style-replicator
License: MIT
Author: shenafield
Author-email: 99119344+shenafield@users.noreply.github.com
Requires-Python: >=3.11,<4.0
Classifier: License :: OSI Approved :: MIT License
Classifier: Programming Language :: Python :: 3
Classifier: Programming Language :: Python :: 3.11
Requires-Dist: click (>=8.1.6,<9.0.0)
Requires-Dist: openai (>=0.27.8,<0.28.0)
Requires-Dist: python-dotenv (>=1.0.0,<2.0.0)
